processeasy/__init__.py
processeasy/data/load_save.py
processeasy/vllm_utils/__init__.py
processeasy/vllm_utils/online_query.py
processeasy-1.2.dist-info/METADATA
processeasy-1.2.dist-info/WHEEL
processeasy-1.2.dist-info/top_level.txt
processeasy-1.2.dist-info/RECORD
