Metadata-Version: 2.4
Name: processeasy
Version: 1.2
Summary: This is the personal use packages
Author-email: Your Name <you@example.com>
License: MIT
Requires-Dist: pandas
Requires-Dist: numpy
Requires-Dist: pyarrow
